auto_classification_generator/__init__.py
auto_classification_generator/classification_generator.py
auto_classification_generator/cli.py
auto_classification_generator/common.py
auto_classification_generator/hash.py
auto_classification_generator/options.properties
auto_classification_generator-1.2.1.dist-info/LICENSE.md
auto_classification_generator-1.2.1.dist-info/METADATA
auto_classification_generator-1.2.1.dist-info/WHEEL
auto_classification_generator-1.2.1.dist-info/entry_points.txt
auto_classification_generator-1.2.1.dist-info/top_level.txt
auto_classification_generator-1.2.1.dist-info/RECORD
