Metadata-Version: 2.1
Name: auto_classification_generator
Version: 1.2.1
Summary: Auto Classification Generator Tool for Archivists
Author-email: Christopher Prince <c.pj.prince@gmail.com>
Project-URL: Homepage, https://github.com/CPJPRINCE/auto_classification_generator
Project-URL: Issues, https://github.com/CPJPRINCE/auto_classification_generator/issues
Classifier: Programming Language :: Python :: 3
Classifier: License :: OSI Approved :: Apache Software License
Classifier: Operating System :: OS Independent
Classifier: Topic :: System :: Archiving
License-File: LICENSE.md
Requires-Dist: pandas
Requires-Dist: openpyxl
